steelas/__init__.py
steelas/__pycache__/__init__.cpython-311.pyc
steelas/component/__init__.py
steelas/component/bolt.py
steelas/component/plate.py
steelas/component/weld.py
steelas/component/__pycache__/__init__.cpython-310.pyc
steelas/component/__pycache__/bolt.cpython-310.pyc
steelas/component/__pycache__/plate.cpython-310.pyc
steelas/component/__pycache__/weld.cpython-310.pyc
steelas/connection/FEP.py
steelas/connection/WSP.py
steelas/connection/__init__.py
steelas/connection/featured_member.py
steelas/connection/__pycache__/FEP.cpython-310.pyc
steelas/connection/__pycache__/WSP.cpython-310.pyc
steelas/connection/__pycache__/__init__.cpython-310.pyc
steelas/connection/__pycache__/featured_member.cpython-310.pyc
steelas/connection/__pycache__/member_stub.cpython-310.pyc
steelas/data/ASI_FEP_connection.csv
steelas/data/ASI_WSP_connection.csv
steelas/data/AUS_bolt_groups.csv
steelas/data/AUS_bolts.csv
steelas/data/AUS_coped_sections.csv
steelas/data/AUS_hollow_sections.csv
steelas/data/AUS_open_sections.csv
steelas/data/AUS_plates.csv
steelas/data/AUS_tee_sections.csv
steelas/data/AUS_welds.csv
steelas/data/__init__.py
steelas/data/io.py
steelas/data/__pycache__/__init__.cpython-311.pyc
steelas/data/__pycache__/io.cpython-311.pyc
steelas/member/__init__.py
steelas/member/geometry.py
steelas/member/material.py
steelas/member/member.py
steelas/member/slenderness.py
steelas/member/__pycache__/__init__.cpython-310.pyc
steelas/member/__pycache__/__init__.cpython-311.pyc
steelas/member/__pycache__/geometry.cpython-310.pyc
steelas/member/__pycache__/geometry.cpython-311.pyc
steelas/member/__pycache__/material.cpython-310.pyc
steelas/member/__pycache__/material.cpython-311.pyc
steelas/member/__pycache__/member.cpython-310.pyc
steelas/member/__pycache__/member.cpython-311.pyc
steelas/member/__pycache__/slenderness.cpython-310.pyc
steelas/member/__pycache__/slenderness.cpython-311.pyc
steelas/shape/__init__.py
steelas/shape/circularhollow.py
steelas/shape/cshape.py
steelas-0.2.0.dist-info/LICENSE
steelas-0.2.0.dist-info/METADATA
steelas-0.2.0.dist-info/WHEEL
steelas-0.2.0.dist-info/top_level.txt
steelas-0.2.0.dist-info/RECORD
