Metadata-Version: 2.1
Name: steelas
Version: 0.2.0
Summary: steelas is a Python package for the design of steel structures to relevant Australian Standards
Author-email: Joe Gattas <j.gattas@uq.edu.au>, Yuyu Wang <yuyu.wang@uq.net.au>
Project-URL: Homepage, https://github.com/Folded-Structures-Lab/steel-as
Keywords: AS4100,steel structures,structural engineering
Classifier: Programming Language :: Python :: 3
Classifier: License :: OSI Approved :: MIT License
Classifier: Operating System :: OS Independent
Requires-Python: >=3.11
License-File: LICENSE
Requires-Dist: numpy >=1.25.0
Requires-Dist: pandas >=2.0.2
